green_box/__init__.py
green_box/green_box.py
green_box-1.3.0.dist-info/METADATA
green_box-1.3.0.dist-info/WHEEL
green_box-1.3.0.dist-info/RECORD
