Metadata-Version: 2.1
Name: green-box
Version: 1.3.0
Summary: Simple data collection from Google Tables
Author: QuoNaro
Author-email: QuoNaro@mail.ru
Requires-Python: >=3.10
Classifier: Programming Language :: Python :: 3
Classifier: Programming Language :: Python :: 3.10
Classifier: Programming Language :: Python :: 3.11
Requires-Dist: numpy (==1.25.1)
Requires-Dist: openpyxl (==3.1.2)
Requires-Dist: requests (==2.31.0)
